{
    "DPAD_CONFIG": "03819CA8",
    "DPAD_TEXTURE": "0381C2E8",
    "EXT_MSG_DATA_FILE": "0381A510",
    "EXT_MSG_TABLE": "0381BCD0",
    "EXT_MSG_TABLE_COUNT": "0381A498",
    "EXT_OBJECTS": "0381A694",
    "FONT_TEXTURE": "0381D2E8",
    "G_C_HEAP": "03820000",
    "G_KALEIDOPAYLOAD_ADDR": "03880000",
    "G_PAYLOAD_ADDR": "03800000",
    "HASH_ICONS": "03819D3C",
    "HUD_COLOR_CONFIG": "03819DAC",
    "ITEM_OVERRIDE_COUNT": "0381A494",
    "ITEM_OVERRIDE_ENTRIES": "0381A850",
    "KALEIDOPAYLOAD_END": "038825C0",
    "KALEIDOPAYLOAD_START": "03880000",
    "MISC_CONFIG": "0381A27C",
    "MMR_CONFIG": "03819ECC",
    "MUSIC_CONFIG": "0381A330",
    "PAYLOAD_END": "0381E7B0",
    "PAYLOAD_START": "03800000",
    "SAVE_FILE_CONFIG": "0381A348",
    "TOWN_FAIRY_BYTES": "03881838",
    "WORLD_COLOR_CONFIG": "0381A424",
    "gExternalEffects": "03819CC4",
    "gHeapNext": "0381A580",
    "gObjheap": "0381C150",
    "gObjheapItems": "0381C168",
    "gPlayUpdateInput": "0381A838",
    "gSetupDb": "0381A3C8",
    "gShouldForceItemSpawn": "0381A4FA",
    "gSpriteDpad": "0381A3B8",
    "gSpriteFont": "0381A3A8",
    "gSpriteIcon": "0381A398",
    "gSpriteIcon24": "0381A388",
    "palmTreeNoNutsDL": "0381BED0"
}
